turbo_chat/__init__.py
turbo_chat/bots/__init__.py
turbo_chat/bots/qa.py
turbo_chat/bots/self_ask.py
turbo_chat/bots/subqueries/__init__.py
turbo_chat/bots/subqueries/bot.py
turbo_chat/bots/subqueries/scratchpad.py
turbo_chat/bots/subqueries/template.py
turbo_chat/bots/summarize.py
turbo_chat/bots/tool/__init__.py
turbo_chat/bots/tool/bot.py
turbo_chat/bots/tool/scratchpad.py
turbo_chat/bots/tool/template.py
turbo_chat/cache/__init__.py
turbo_chat/cache/redis.py
turbo_chat/cache/simple.py
turbo_chat/chat.py
turbo_chat/completion.py
turbo_chat/config.py
turbo_chat/errors.py
turbo_chat/memory/__init__.py
turbo_chat/memory/local_memory.py
turbo_chat/memory/summary_memory.py
turbo_chat/memory/truncated_memory.py
turbo_chat/runner.py
turbo_chat/structs/__init__.py
turbo_chat/structs/messages.py
turbo_chat/structs/proxies.py
turbo_chat/structs/result.py
turbo_chat/structs/scratchpad.py
turbo_chat/structs/signals.py
turbo_chat/turbo.py
turbo_chat/types/__init__.py
turbo_chat/types/cache.py
turbo_chat/types/generators.py
turbo_chat/types/memory.py
turbo_chat/types/messages.py
turbo_chat/types/misc.py
turbo_chat/types/tools.py
turbo_chat/utils/__init__.py
turbo_chat/utils/args.py
turbo_chat/utils/cl100k_base.tiktoken
turbo_chat/utils/debug.py
turbo_chat/utils/fn.py
turbo_chat/utils/lang.py
turbo_chat/utils/pprint.py
turbo_chat/utils/retries.py
turbo_chat/utils/template.py
turbo_chat/utils/tokens.py
turbo_ai-0.3.12.dist-info/LICENSE
turbo_ai-0.3.12.dist-info/METADATA
turbo_ai-0.3.12.dist-info/WHEEL
turbo_ai-0.3.12.dist-info/RECORD
