Metadata-Version: 2.1
Name: turbo-ai
Version: 0.3.12
Summary: Idiomatic way to build chatgpt apps using async generators in python
License: MIT
Author: Diwank Singh Tomer
Author-email: singh@diwank.name
Requires-Python: >=3.8,<3.11
Classifier: License :: OSI Approved :: MIT License
Classifier: Programming Language :: Python :: 3
Classifier: Programming Language :: Python :: 3.8
Classifier: Programming Language :: Python :: 3.9
Classifier: Programming Language :: Python :: 3.10
Provides-Extra: debug
Provides-Extra: redis
Requires-Dist: aiochan (>=0.2.7,<0.3.0)
Requires-Dist: aiohttp (>=3.8.4,<4.0.0)
Requires-Dist: blobfile (>=2.0.1,<3.0.0)
Requires-Dist: cloudevents (>=1.9.0,<2.0.0)
Requires-Dist: colorama (>=0.4.6,<0.5.0) ; extra == "debug"
Requires-Dist: dirtyjson (>=1.0.8,<2.0.0)
Requires-Dist: duckdb (>=0.8.0,<0.9.0)
Requires-Dist: jinja2 (>=3.1.2,<4.0.0)
Requires-Dist: lemminflect (>=0.2.3,<0.3.0)
Requires-Dist: openai (>=0.27.7,<0.28.0)
Requires-Dist: pandas (>=2.0.1,<3.0.0)
Requires-Dist: parse (>=1.19.0,<2.0.0)
Requires-Dist: pyarrow (>=12.0.0,<13.0.0)
Requires-Dist: pydantic (>=1.10.8,<2.0.0)
Requires-Dist: pygments (>=2.15.0,<3.0.0) ; extra == "debug"
Requires-Dist: pylance (>=0.4.15,<0.5.0)
Requires-Dist: pyrsistent (>=0.19.3,<0.20.0)
Requires-Dist: redis (>=4.5.0,<5.0.0) ; extra == "redis"
Requires-Dist: tenacity (>=8.2.2,<9.0.0)
Requires-Dist: tiktoken (>=0.4.0,<0.5.0)
